singularity_permanent_cache/__init__.py
singularity_permanent_cache/singularity_permanent_cache.py
singularity_permanent_cache-1.0.0a0.dist-info/LICENSE
singularity_permanent_cache-1.0.0a0.dist-info/METADATA
singularity_permanent_cache-1.0.0a0.dist-info/WHEEL
singularity_permanent_cache-1.0.0a0.dist-info/entry_points.txt
singularity_permanent_cache-1.0.0a0.dist-info/top_level.txt
singularity_permanent_cache-1.0.0a0.dist-info/RECORD
