Metadata-Version: 2.1
Name: singularity-permanent-cache
Version: 1.0.0a0
Summary: Creates a permanent cache for singularity images on disk.
Home-page: https://github.com/BioWDL/singularity-permanent-cache
Author: Leiden University Medical Center
Author-email: sasc@lumc.nl
License: MIT
Keywords: singularity cache permanent hpc
Platform: UNKNOWN
Classifier: Programming Language :: Python :: 3 :: Only
Classifier: Programming Language :: Python :: 3
Classifier: Programming Language :: Python :: 3.5
Classifier: Programming Language :: Python :: 3.6
Classifier: Programming Language :: Python :: 3.7
Classifier: Programming Language :: Python :: 3.8
Classifier: Development Status :: 3 - Alpha
Classifier: License :: OSI Approved :: MIT License
Classifier: Operating System :: Unix
Classifier: Typing :: Typed
Requires-Python: >=3.5
